sitepy/__init__.py
sitepy/core.py
sitepy/gpt.py
sitepy/log.py
sitepy/profanity.py
sitepy/recaptcha.py
sitepy/word_list.py
sitepy-0.4.6.dist-info/LICENSE
sitepy-0.4.6.dist-info/METADATA
sitepy-0.4.6.dist-info/WHEEL
sitepy-0.4.6.dist-info/top_level.txt
sitepy-0.4.6.dist-info/RECORD
