Metadata-Version: 2.1
Name: sitepy
Version: 0.4.6
Summary: A simple web framework.
Home-page: https://github.com/WolfTheDeveloper/sitepy
Author: WolfTheDev
Author-email: wolfthedev@gmail.com
License: Copyright [2024] [WolfTheDev]
Classifier: Development Status :: 3 - Alpha
Classifier: Intended Audience :: Developers
Classifier: License :: OSI Approved :: Apache Software License
Classifier: Programming Language :: Python :: 3.6
Classifier: Programming Language :: Python :: 3.7
Classifier: Programming Language :: Python :: 3.8
Classifier: Programming Language :: Python :: 3.9
Classifier: Programming Language :: Python :: 3.10
Classifier: Programming Language :: Python :: 3.11
Classifier: Programming Language :: Python :: 3.12
Classifier: Topic :: Software Development :: Libraries :: Python Modules
Requires-Python: >=3.6
License-File: LICENSE
